{
  "session_id": "938cecba-2b62-4c64-b43d-4acfa50296b3",
  "profile_id": "tiktok_ds",
  "resume_id": "resume_MLE",
  "mode": "realistic",
  "length_type": "questions",
  "hint_level": "standard",
  "focus_category": null,
  "num_questions": 5,
  "time_limit": null,
  "question_plan": [
    {
      "index": 0,
      "type": "intro"
    },
    {
      "index": 1,
      "type": "project"
    },
    {
      "index": 2,
      "type": "technical"
    },
    {
      "index": 3,
      "type": "case"
    },
    {
      "index": 4,
      "type": "behavioral"
    }
  ],
  "created_at": "2025-12-10T16:53:56.616337",
  "completed": false,
  "used_question_ids": [],
  "used_question_slugs": [],
  "used_question_texts": [],
  "interviewer_profile": {
    "gender": "male",
    "role_preset": "hiring_manager",
    "role_resolved": "the hiring manager who cares about team fit, ownership, and impact",
    "style_preset": "balanced",
    "style_resolved": "balanced, neutral but probing",
    "extra_notes": "",
    "tts_persona": "the hiring manager who cares about team fit, ownership, and impact. balanced, neutral but probing."
  },
  "primary_project_entry_key": "PROJECTS||YouBike Prediction Service Jun 2025 - Present"
}